[
  {
    "id": "95c55a7b-789e-11ec-ae92-0242ac120002",
    "name": null,
    "ordinal": 1,
    "opening": {
      "stop": null,
      "start": null
    },
    "ending": {
      "stop": null,
      "start": null
    },
    "preview": {
      "src": null,
      "preview": null,
      "thumbnail": null,
      "optimized": {
        "src": null,
        "preview": null,
        "thumbnail": null
      }
    },
    "hls_480": "https://cache.libria.fun/videos/media/ts/8050/1/480/459430b9a911fa763ce4ff4f901dcca3.m3u8?countryIso=US&isAuthorized=0&isWithVideoAds=1&isWithVideoAdsAlways=1",
    "hls_720": "https://cache.libria.fun/videos/media/ts/8050/1/720/e8acb42e9197a6117fef603a22b5df15.m3u8?countryIso=US&isAuthorized=0&isWithVideoAds=1&isWithVideoAdsAlways=1",
    "hls_1080": null,
    "duration": 1452,
    "rutube_id": null,
    "youtube_id": null,
    "updated_at": "2019-01-15T19:46:22+00:00",
    "sort_order": 1,
    "release_id": 8050,
    "name_english": null,
    "_stream_links": {
      "hls_720": "https://cache.libria.fun/videos/media/ts/8050/1/720/e8acb42e9197a6117fef603a22b5df15.m3u8?countryIso=US&isAuthorized=0&isWithVideoAds=1&isWithVideoAdsAlways=1",
      "hls_480": "https://cache.libria.fun/videos/media/ts/8050/1/480/459430b9a911fa763ce4ff4f901dcca3.m3u8?countryIso=US&isAuthorized=0&isWithVideoAds=1&isWithVideoAdsAlways=1"
    }
  },
  {
    "id": "95c55ae4-789e-11ec-ae92-0242ac120002",
    "name": null,
    "ordinal": 2,
    "opening": {
      "stop": 160,
      "start": 71
    },
    "ending": {
      "stop": null,
      "start": null
    },
    "preview": {
      "src": null,
      "preview": null,
      "thumbnail": null,
      "optimized": {
        "src": null,
        "preview": null,
        "thumbnail": null
      }
    },
    "hls_480": "https://cache.libria.fun/videos/media/ts/8050/2/480/4a98fa08ea8461478494a07f93c34fa6.m3u8?countryIso=US&isAuthorized=0&isWithVideoAds=1&isWithVideoAdsAlways=1",
    "hls_720": "https://cache.libria.fun/videos/media/ts/8050/2/720/3fadb93686aa5b51a13e53840131929b.m3u8?countryIso=US&isAuthorized=0&isWithVideoAds=1&isWithVideoAdsAlways=1",
    "hls_1080": null,
    "duration": 1452,
    "rutube_id": null,
    "youtube_id": null,
    "updated_at": "2019-01-20T10:55:42+00:00",
    "sort_order": 2,
    "release_id": 8050,
    "name_english": null,
    "_stream_links": {
      "hls_720": "https://cache.libria.fun/videos/media/ts/8050/2/720/3fadb93686aa5b51a13e53840131929b.m3u8?countryIso=US&isAuthorized=0&isWithVideoAds=1&isWithVideoAdsAlways=1",
      "hls_480": "https://cache.libria.fun/videos/media/ts/8050/2/480/4a98fa08ea8461478494a07f93c34fa6.m3u8?countryIso=US&isAuthorized=0&isWithVideoAds=1&isWithVideoAdsAlways=1"
    }
  },
  {
    "id": "95c55bfa-789e-11ec-ae92-0242ac120002",
    "name": null,
    "ordinal": 3,
    "opening": {
      "stop": 176,
      "start": 88
    },
    "ending": {
      "stop": null,
      "start": null
    },
    "preview": {
      "src": null,
      "preview": null,
      "thumbnail": null,
      "optimized": {
        "src": null,
        "preview": null,
        "thumbnail": null
      }
    },
    "hls_480": "https://cache.libria.fun/videos/media/ts/8050/3/480/7b549a1dbf5d6a7a8a67b04fc2ae0ea2.m3u8?countryIso=US&isAuthorized=0&isWithVideoAds=1&isWithVideoAdsAlways=1",
    "hls_720": "https://cache.libria.fun/videos/media/ts/8050/3/720/094b1899a68c157b3472b951fa413dbd.m3u8?countryIso=US&isAuthorized=0&isWithVideoAds=1&isWithVideoAdsAlways=1",
    "hls_1080": null,
    "duration": 1467,
    "rutube_id": null,
    "youtube_id": null,
    "updated_at": "2019-01-26T16:21:35+00:00",
    "sort_order": 3,
    "release_id": 8050,
    "name_english": null,
    "_stream_links": {
      "hls_720": "https://cache.libria.fun/videos/media/ts/8050/3/720/094b1899a68c157b3472b951fa413dbd.m3u8?countryIso=US&isAuthorized=0&isWithVideoAds=1&isWithVideoAdsAlways=1",
      "hls_480": "https://cache.libria.fun/videos/media/ts/8050/3/480/7b549a1dbf5d6a7a8a67b04fc2ae0ea2.m3u8?countryIso=US&isAuthorized=0&isWithVideoAds=1&isWithVideoAdsAlways=1"
    }
  },
  {
    "id": "95c55db9-789e-11ec-ae92-0242ac120002",
    "name": null,
    "ordinal": 4,
    "opening": {
      "stop": 146,
      "start": 57
    },
    "ending": {
      "stop": null,
      "start": null
    },
    "preview": {
      "src": null,
      "preview": null,
      "thumbnail": null,
      "optimized": {
        "src": null,
        "preview": null,
        "thumbnail": null
      }
    },
    "hls_480": "https://cache.libria.fun/videos/media/ts/8050/4/480/4ca61fb00cfeda28a2f1e2c1633df44c.m3u8?countryIso=US&isAuthorized=0&isWithVideoAds=1&isWithVideoAdsAlways=1",
    "hls_720": "https://cache.libria.fun/videos/media/ts/8050/4/720/2f601e2fc62a131436a3e1ad2e88c4e3.m3u8?countryIso=US&isAuthorized=0&isWithVideoAds=1&isWithVideoAdsAlways=1",
    "hls_1080": null,
    "duration": 1467,
    "rutube_id": null,
    "youtube_id": null,
    "updated_at": "2019-02-02T19:47:40+00:00",
    "sort_order": 4,
    "release_id": 8050,
    "name_english": null,
    "_stream_links": {
      "hls_720": "https://cache.libria.fun/videos/media/ts/8050/4/720/2f601e2fc62a131436a3e1ad2e88c4e3.m3u8?countryIso=US&isAuthorized=0&isWithVideoAds=1&isWithVideoAdsAlways=1",
      "hls_480": "https://cache.libria.fun/videos/media/ts/8050/4/480/4ca61fb00cfeda28a2f1e2c1633df44c.m3u8?countryIso=US&isAuthorized=0&isWithVideoAds=1&isWithVideoAdsAlways=1"
    }
  },
  {
    "id": "95c55e37-789e-11ec-ae92-0242ac120002",
    "name": null,
    "ordinal": 5,
    "opening": {
      "stop": 119,
      "start": 31
    },
    "ending": {
      "stop": null,
      "start": null
    },
    "preview": {
      "src": null,
      "preview": null,
      "thumbnail": null,
      "optimized": {
        "src": null,
        "preview": null,
        "thumbnail": null
      }
    },
    "hls_480": "https://cache.libria.fun/videos/media/ts/8050/5/480/dc5d5e46c107b6c99c57442622acb4f6.m3u8?countryIso=US&isAuthorized=0&isWithVideoAds=1&isWithVideoAdsAlways=1",
    "hls_720": "https://cache.libria.fun/videos/media/ts/8050/5/720/1f2ef2041e127634cda2dfc5ff84d2e7.m3u8?countryIso=US&isAuthorized=0&isWithVideoAds=1&isWithVideoAdsAlways=1",
    "hls_1080": null,
    "duration": 1467,
    "rutube_id": null,
    "youtube_id": null,
    "updated_at": "2019-02-10T19:00:57+00:00",
    "sort_order": 5,
    "release_id": 8050,
    "name_english": null,
    "_stream_links": {
      "hls_720": "https://cache.libria.fun/videos/media/ts/8050/5/720/1f2ef2041e127634cda2dfc5ff84d2e7.m3u8?countryIso=US&isAuthorized=0&isWithVideoAds=1&isWithVideoAdsAlways=1",
      "hls_480": "https://cache.libria.fun/videos/media/ts/8050/5/480/dc5d5e46c107b6c99c57442622acb4f6.m3u8?countryIso=US&isAuthorized=0&isWithVideoAds=1&isWithVideoAdsAlways=1"
    }
  },
  {
    "id": "95c55eb3-789e-11ec-ae92-0242ac120002",
    "name": null,
    "ordinal": 6,
    "opening": {
      "stop": 164,
      "start": 75
    },
    "ending": {
      "stop": null,
      "start": null
    },
    "preview": {
      "src": null,
      "preview": null,
      "thumbnail": null,
      "optimized": {
        "src": null,
        "preview": null,
        "thumbnail": null
      }
    },
    "hls_480": "https://cache.libria.fun/videos/media/ts/8050/6/480/f209ade201a832028ac7aabf60cd0f66.m3u8?countryIso=US&isAuthorized=0&isWithVideoAds=1&isWithVideoAdsAlways=1",
    "hls_720": "https://cache.libria.fun/videos/media/ts/8050/6/720/63624b37c399b3f464eecf0251cafe11.m3u8?countryIso=US&isAuthorized=0&isWithVideoAds=1&isWithVideoAdsAlways=1",
    "hls_1080": null,
    "duration": 1467,
    "rutube_id": null,
    "youtube_id": null,
    "updated_at": "2019-02-18T17:04:43+00:00",
    "sort_order": 6,
    "release_id": 8050,
    "name_english": null,
    "_stream_links": {
      "hls_720": "https://cache.libria.fun/videos/media/ts/8050/6/720/63624b37c399b3f464eecf0251cafe11.m3u8?countryIso=US&isAuthorized=0&isWithVideoAds=1&isWithVideoAdsAlways=1",
      "hls_480": "https://cache.libria.fun/videos/media/ts/8050/6/480/f209ade201a832028ac7aabf60cd0f66.m3u8?countryIso=US&isAuthorized=0&isWithVideoAds=1&isWithVideoAdsAlways=1"
    }
  },
  {
    "id": "95c55f2f-789e-11ec-ae92-0242ac120002",
    "name": null,
    "ordinal": 7,
    "opening": {
      "stop": 234,
      "start": 146
    },
    "ending": {
      "stop": null,
      "start": null
    },
    "preview": {
      "src": null,
      "preview": null,
      "thumbnail": null,
      "optimized": {
        "src": null,
        "preview": null,
        "thumbnail": null
      }
    },
    "hls_480": "https://cache.libria.fun/videos/media/ts/8050/7/480/a2d20119333d49a3d7064bda57b0310e.m3u8?countryIso=US&isAuthorized=0&isWithVideoAds=1&isWithVideoAdsAlways=1",
    "hls_720": "https://cache.libria.fun/videos/media/ts/8050/7/720/1a884661ce6a859c9815f8c8308c1199.m3u8?countryIso=US&isAuthorized=0&isWithVideoAds=1&isWithVideoAdsAlways=1",
    "hls_1080": null,
    "duration": 1467,
    "rutube_id": null,
    "youtube_id": null,
    "updated_at": "2019-03-02T09:18:08+00:00",
    "sort_order": 7,
    "release_id": 8050,
    "name_english": null,
    "_stream_links": {
      "hls_720": "https://cache.libria.fun/videos/media/ts/8050/7/720/1a884661ce6a859c9815f8c8308c1199.m3u8?countryIso=US&isAuthorized=0&isWithVideoAds=1&isWithVideoAdsAlways=1",
      "hls_480": "https://cache.libria.fun/videos/media/ts/8050/7/480/a2d20119333d49a3d7064bda57b0310e.m3u8?countryIso=US&isAuthorized=0&isWithVideoAds=1&isWithVideoAdsAlways=1"
    }
  },
  {
    "id": "95c55fac-789e-11ec-ae92-0242ac120002",
    "name": null,
    "ordinal": 8,
    "opening": {
      "stop": 248,
      "start": 160
    },
    "ending": {
      "stop": null,
      "start": null
    },
    "preview": {
      "src": null,
      "preview": null,
      "thumbnail": null,
      "optimized": {
        "src": null,
        "preview": null,
        "thumbnail": null
      }
    },
    "hls_480": "https://cache.libria.fun/videos/media/ts/8050/8/480/3d3fe7607f388cfe994c1d766a022735.m3u8?countryIso=US&isAuthorized=0&isWithVideoAds=1&isWithVideoAdsAlways=1",
    "hls_720": "https://cache.libria.fun/videos/media/ts/8050/8/720/b054bed91b5b5b5914410bc9d58ee128.m3u8?countryIso=US&isAuthorized=0&isWithVideoAds=1&isWithVideoAdsAlways=1",
    "hls_1080": null,
    "duration": 1452,
    "rutube_id": null,
    "youtube_id": null,
    "updated_at": "2019-03-06T19:40:56+00:00",
    "sort_order": 8,
    "release_id": 8050,
    "name_english": null,
    "_stream_links": {
      "hls_720": "https://cache.libria.fun/videos/media/ts/8050/8/720/b054bed91b5b5b5914410bc9d58ee128.m3u8?countryIso=US&isAuthorized=0&isWithVideoAds=1&isWithVideoAdsAlways=1",
      "hls_480": "https://cache.libria.fun/videos/media/ts/8050/8/480/3d3fe7607f388cfe994c1d766a022735.m3u8?countryIso=US&isAuthorized=0&isWithVideoAds=1&isWithVideoAdsAlways=1"
    }
  },
  {
    "id": "95c5602a-789e-11ec-ae92-0242ac120002",
    "name": null,
    "ordinal": 9,
    "opening": {
      "stop": 167,
      "start": 75
    },
    "ending": {
      "stop": null,
      "start": null
    },
    "preview": {
      "src": null,
      "preview": null,
      "thumbnail": null,
      "optimized": {
        "src": null,
        "preview": null,
        "thumbnail": null
      }
    },
    "hls_480": "https://cache.libria.fun/videos/media/ts/8050/9/480/8fcfd1cea7e46223676ff865fdf0e100.m3u8?countryIso=US&isAuthorized=0&isWithVideoAds=1&isWithVideoAdsAlways=1",
    "hls_720": "https://cache.libria.fun/videos/media/ts/8050/9/720/d746e000f877a60371e21d1a994e8e2f.m3u8?countryIso=US&isAuthorized=0&isWithVideoAds=1&isWithVideoAdsAlways=1",
    "hls_1080": null,
    "duration": 1452,
    "rutube_id": null,
    "youtube_id": null,
    "updated_at": "2019-03-09T19:52:02+00:00",
    "sort_order": 9,
    "release_id": 8050,
    "name_english": null,
    "_stream_links": {
      "hls_720": "https://cache.libria.fun/videos/media/ts/8050/9/720/d746e000f877a60371e21d1a994e8e2f.m3u8?countryIso=US&isAuthorized=0&isWithVideoAds=1&isWithVideoAdsAlways=1",
      "hls_480": "https://cache.libria.fun/videos/media/ts/8050/9/480/8fcfd1cea7e46223676ff865fdf0e100.m3u8?countryIso=US&isAuthorized=0&isWithVideoAds=1&isWithVideoAdsAlways=1"
    }
  },
  {
    "id": "95c560a6-789e-11ec-ae92-0242ac120002",
    "name": null,
    "ordinal": 10,
    "opening": {
      "stop": 165,
      "start": 71
    },
    "ending": {
      "stop": null,
      "start": null
    },
    "preview": {
      "src": null,
      "preview": null,
      "thumbnail": null,
      "optimized": {
        "src": null,
        "preview": null,
        "thumbnail": null
      }
    },
    "hls_480": "https://cache.libria.fun/videos/media/ts/8050/10/480/6f7ed7a7a91b4ab82384905870631355.m3u8?countryIso=US&isAuthorized=0&isWithVideoAds=1&isWithVideoAdsAlways=1",
    "hls_720": "https://cache.libria.fun/videos/media/ts/8050/10/720/f18e269ba39afb86b95d3b198955ffc5.m3u8?countryIso=US&isAuthorized=0&isWithVideoAds=1&isWithVideoAdsAlways=1",
    "hls_1080": null,
    "duration": 1452,
    "rutube_id": null,
    "youtube_id": null,
    "updated_at": "2019-03-17T15:23:31+00:00",
    "sort_order": 10,
    "release_id": 8050,
    "name_english": null,
    "_stream_links": {
      "hls_720": "https://cache.libria.fun/videos/media/ts/8050/10/720/f18e269ba39afb86b95d3b198955ffc5.m3u8?countryIso=US&isAuthorized=0&isWithVideoAds=1&isWithVideoAdsAlways=1",
      "hls_480": "https://cache.libria.fun/videos/media/ts/8050/10/480/6f7ed7a7a91b4ab82384905870631355.m3u8?countryIso=US&isAuthorized=0&isWithVideoAds=1&isWithVideoAdsAlways=1"
    }
  },
  {
    "id": "95c56123-789e-11ec-ae92-0242ac120002",
    "name": null,
    "ordinal": 11,
    "opening": {
      "stop": 145,
      "start": 55
    },
    "ending": {
      "stop": null,
      "start": null
    },
    "preview": {
      "src": null,
      "preview": null,
      "thumbnail": null,
      "optimized": {
        "src": null,
        "preview": null,
        "thumbnail": null
      }
    },
    "hls_480": "https://cache.libria.fun/videos/media/ts/8050/11/480/5d4548cb6603e113e86f09f8662c1ee3.m3u8?countryIso=US&isAuthorized=0&isWithVideoAds=1&isWithVideoAdsAlways=1",
    "hls_720": "https://cache.libria.fun/videos/media/ts/8050/11/720/47870988ab886f2bfef82601e091a645.m3u8?countryIso=US&isAuthorized=0&isWithVideoAds=1&isWithVideoAdsAlways=1",
    "hls_1080": null,
    "duration": 1452,
    "rutube_id": null,
    "youtube_id": null,
    "updated_at": "2019-03-29T19:49:16+00:00",
    "sort_order": 11,
    "release_id": 8050,
    "name_english": null,
    "_stream_links": {
      "hls_720": "https://cache.libria.fun/videos/media/ts/8050/11/720/47870988ab886f2bfef82601e091a645.m3u8?countryIso=US&isAuthorized=0&isWithVideoAds=1&isWithVideoAdsAlways=1",
      "hls_480": "https://cache.libria.fun/videos/media/ts/8050/11/480/5d4548cb6603e113e86f09f8662c1ee3.m3u8?countryIso=US&isAuthorized=0&isWithVideoAds=1&isWithVideoAdsAlways=1"
    }
  },
  {
    "id": "95c5619f-789e-11ec-ae92-0242ac120002",
    "name": null,
    "ordinal": 12,
    "opening": {
      "stop": null,
      "start": null
    },
    "ending": {
      "stop": null,
      "start": null
    },
    "preview": {
      "src": null,
      "preview": null,
      "thumbnail": null,
      "optimized": {
        "src": null,
        "preview": null,
        "thumbnail": null
      }
    },
    "hls_480": "https://cache.libria.fun/videos/media/ts/8050/12/480/7cf8cd9f8e45a944a3274c905f832911.m3u8?countryIso=US&isAuthorized=0&isWithVideoAds=1&isWithVideoAdsAlways=1",
    "hls_720": "https://cache.libria.fun/videos/media/ts/8050/12/720/9efde564e74d6b229741d8471dee9f9c.m3u8?countryIso=US&isAuthorized=0&isWithVideoAds=1&isWithVideoAdsAlways=1",
    "hls_1080": null,
    "duration": 1452,
    "rutube_id": null,
    "youtube_id": null,
    "updated_at": "2019-03-31T11:34:19+00:00",
    "sort_order": 12,
    "release_id": 8050,
    "name_english": null,
    "_stream_links": {
      "hls_720": "https://cache.libria.fun/videos/media/ts/8050/12/720/9efde564e74d6b229741d8471dee9f9c.m3u8?countryIso=US&isAuthorized=0&isWithVideoAds=1&isWithVideoAdsAlways=1",
      "hls_480": "https://cache.libria.fun/videos/media/ts/8050/12/480/7cf8cd9f8e45a944a3274c905f832911.m3u8?countryIso=US&isAuthorized=0&isWithVideoAds=1&isWithVideoAdsAlways=1"
    }
  }
]