[
  {
    "id": "95c758ad-789e-11ec-ae92-0242ac120002",
    "name": null,
    "ordinal": 1,
    "opening": {
      "stop": null,
      "start": null
    },
    "ending": {
      "stop": null,
      "start": null
    },
    "preview": {
      "src": null,
      "preview": null,
      "thumbnail": null,
      "optimized": {
        "src": null,
        "preview": null,
        "thumbnail": null
      }
    },
    "hls_480": "https://cache.libria.fun/videos/media/ts/8353/1/480/095ce8b6251c187cf1f316cbf522b2fa.m3u8?countryIso=US&isAuthorized=0&isWithVideoAds=1&isWithVideoAdsAlways=1",
    "hls_720": "https://cache.libria.fun/videos/media/ts/8353/1/720/05b17a9553585fa946817a2d230f65db.m3u8?countryIso=US&isAuthorized=0&isWithVideoAds=1&isWithVideoAdsAlways=1",
    "hls_1080": null,
    "duration": 1409,
    "rutube_id": null,
    "youtube_id": null,
    "updated_at": "2019-04-03T22:30:57+00:00",
    "sort_order": 1,
    "release_id": 8353,
    "name_english": null,
    "_stream_links": {
      "hls_720": "https://cache.libria.fun/videos/media/ts/8353/1/720/05b17a9553585fa946817a2d230f65db.m3u8?countryIso=US&isAuthorized=0&isWithVideoAds=1&isWithVideoAdsAlways=1",
      "hls_480": "https://cache.libria.fun/videos/media/ts/8353/1/480/095ce8b6251c187cf1f316cbf522b2fa.m3u8?countryIso=US&isAuthorized=0&isWithVideoAds=1&isWithVideoAdsAlways=1"
    }
  },
  {
    "id": "95c7591e-789e-11ec-ae92-0242ac120002",
    "name": null,
    "ordinal": 2,
    "opening": {
      "stop": 108,
      "start": 23
    },
    "ending": {
      "stop": null,
      "start": null
    },
    "preview": {
      "src": null,
      "preview": null,
      "thumbnail": null,
      "optimized": {
        "src": null,
        "preview": null,
        "thumbnail": null
      }
    },
    "hls_480": "https://cache.libria.fun/videos/media/ts/8353/2/480/506f483e0d09468ae038ac43dc1a8f25.m3u8?countryIso=US&isAuthorized=0&isWithVideoAds=1&isWithVideoAdsAlways=1",
    "hls_720": "https://cache.libria.fun/videos/media/ts/8353/2/720/62c7626c3a467faef0553684491dcbec.m3u8?countryIso=US&isAuthorized=0&isWithVideoAds=1&isWithVideoAdsAlways=1",
    "hls_1080": null,
    "duration": 1470,
    "rutube_id": null,
    "youtube_id": null,
    "updated_at": "2019-04-03T22:30:15+00:00",
    "sort_order": 2,
    "release_id": 8353,
    "name_english": null,
    "_stream_links": {
      "hls_720": "https://cache.libria.fun/videos/media/ts/8353/2/720/62c7626c3a467faef0553684491dcbec.m3u8?countryIso=US&isAuthorized=0&isWithVideoAds=1&isWithVideoAdsAlways=1",
      "hls_480": "https://cache.libria.fun/videos/media/ts/8353/2/480/506f483e0d09468ae038ac43dc1a8f25.m3u8?countryIso=US&isAuthorized=0&isWithVideoAds=1&isWithVideoAdsAlways=1"
    }
  },
  {
    "id": "95c7598d-789e-11ec-ae92-0242ac120002",
    "name": null,
    "ordinal": 3,
    "opening": {
      "stop": null,
      "start": null
    },
    "ending": {
      "stop": null,
      "start": null
    },
    "preview": {
      "src": null,
      "preview": null,
      "thumbnail": null,
      "optimized": {
        "src": null,
        "preview": null,
        "thumbnail": null
      }
    },
    "hls_480": "https://cache.libria.fun/videos/media/ts/8353/3/480/46cb9f06fb2d25a29e3ecd0a5cbb844c.m3u8?countryIso=US&isAuthorized=0&isWithVideoAds=1&isWithVideoAdsAlways=1",
    "hls_720": "https://cache.libria.fun/videos/media/ts/8353/3/720/51fd6ff78cac6b25c5b9d3d22c764ac9.m3u8?countryIso=US&isAuthorized=0&isWithVideoAds=1&isWithVideoAdsAlways=1",
    "hls_1080": null,
    "duration": 1470,
    "rutube_id": null,
    "youtube_id": null,
    "updated_at": "2019-04-03T22:30:11+00:00",
    "sort_order": 3,
    "release_id": 8353,
    "name_english": null,
    "_stream_links": {
      "hls_720": "https://cache.libria.fun/videos/media/ts/8353/3/720/51fd6ff78cac6b25c5b9d3d22c764ac9.m3u8?countryIso=US&isAuthorized=0&isWithVideoAds=1&isWithVideoAdsAlways=1",
      "hls_480": "https://cache.libria.fun/videos/media/ts/8353/3/480/46cb9f06fb2d25a29e3ecd0a5cbb844c.m3u8?countryIso=US&isAuthorized=0&isWithVideoAds=1&isWithVideoAdsAlways=1"
    }
  },
  {
    "id": "95c759fe-789e-11ec-ae92-0242ac120002",
    "name": null,
    "ordinal": 4,
    "opening": {
      "stop": null,
      "start": null
    },
    "ending": {
      "stop": null,
      "start": null
    },
    "preview": {
      "src": null,
      "preview": null,
      "thumbnail": null,
      "optimized": {
        "src": null,
        "preview": null,
        "thumbnail": null
      }
    },
    "hls_480": "https://cache.libria.fun/videos/media/ts/8353/4/480/55e6e7dbb8dbbecb33947edfdaf91556.m3u8?countryIso=US&isAuthorized=0&isWithVideoAds=1&isWithVideoAdsAlways=1",
    "hls_720": "https://cache.libria.fun/videos/media/ts/8353/4/720/8eea1333293abb5c6a1068fdb8283617.m3u8?countryIso=US&isAuthorized=0&isWithVideoAds=1&isWithVideoAdsAlways=1",
    "hls_1080": null,
    "duration": 1470,
    "rutube_id": null,
    "youtube_id": null,
    "updated_at": "2019-04-03T22:29:24+00:00",
    "sort_order": 4,
    "release_id": 8353,
    "name_english": null,
    "_stream_links": {
      "hls_720": "https://cache.libria.fun/videos/media/ts/8353/4/720/8eea1333293abb5c6a1068fdb8283617.m3u8?countryIso=US&isAuthorized=0&isWithVideoAds=1&isWithVideoAdsAlways=1",
      "hls_480": "https://cache.libria.fun/videos/media/ts/8353/4/480/55e6e7dbb8dbbecb33947edfdaf91556.m3u8?countryIso=US&isAuthorized=0&isWithVideoAds=1&isWithVideoAdsAlways=1"
    }
  },
  {
    "id": "95c75a6f-789e-11ec-ae92-0242ac120002",
    "name": null,
    "ordinal": 5,
    "opening": {
      "stop": null,
      "start": null
    },
    "ending": {
      "stop": null,
      "start": null
    },
    "preview": {
      "src": null,
      "preview": null,
      "thumbnail": null,
      "optimized": {
        "src": null,
        "preview": null,
        "thumbnail": null
      }
    },
    "hls_480": "https://cache.libria.fun/videos/media/ts/8353/5/480/6d1f8e1c1f29c237d31292361735fe72.m3u8?countryIso=US&isAuthorized=0&isWithVideoAds=1&isWithVideoAdsAlways=1",
    "hls_720": "https://cache.libria.fun/videos/media/ts/8353/5/720/f3f9fe45483f7e2804a9936768b9520d.m3u8?countryIso=US&isAuthorized=0&isWithVideoAds=1&isWithVideoAdsAlways=1",
    "hls_1080": null,
    "duration": 1470,
    "rutube_id": null,
    "youtube_id": null,
    "updated_at": "2019-04-03T22:29:22+00:00",
    "sort_order": 5,
    "release_id": 8353,
    "name_english": null,
    "_stream_links": {
      "hls_720": "https://cache.libria.fun/videos/media/ts/8353/5/720/f3f9fe45483f7e2804a9936768b9520d.m3u8?countryIso=US&isAuthorized=0&isWithVideoAds=1&isWithVideoAdsAlways=1",
      "hls_480": "https://cache.libria.fun/videos/media/ts/8353/5/480/6d1f8e1c1f29c237d31292361735fe72.m3u8?countryIso=US&isAuthorized=0&isWithVideoAds=1&isWithVideoAdsAlways=1"
    }
  },
  {
    "id": "95c75ae2-789e-11ec-ae92-0242ac120002",
    "name": null,
    "ordinal": 6,
    "opening": {
      "stop": 85,
      "start": 37
    },
    "ending": {
      "stop": null,
      "start": null
    },
    "preview": {
      "src": null,
      "preview": null,
      "thumbnail": null,
      "optimized": {
        "src": null,
        "preview": null,
        "thumbnail": null
      }
    },
    "hls_480": "https://cache.libria.fun/videos/media/ts/8353/6/480/f425248393dc0aaebb0d20d1f383bc9a.m3u8?countryIso=US&isAuthorized=0&isWithVideoAds=1&isWithVideoAdsAlways=1",
    "hls_720": "https://cache.libria.fun/videos/media/ts/8353/6/720/89867b8748680da8028063b5a10e37b2.m3u8?countryIso=US&isAuthorized=0&isWithVideoAds=1&isWithVideoAdsAlways=1",
    "hls_1080": null,
    "duration": 1470,
    "rutube_id": null,
    "youtube_id": null,
    "updated_at": "2019-04-03T22:28:19+00:00",
    "sort_order": 6,
    "release_id": 8353,
    "name_english": null,
    "_stream_links": {
      "hls_720": "https://cache.libria.fun/videos/media/ts/8353/6/720/89867b8748680da8028063b5a10e37b2.m3u8?countryIso=US&isAuthorized=0&isWithVideoAds=1&isWithVideoAdsAlways=1",
      "hls_480": "https://cache.libria.fun/videos/media/ts/8353/6/480/f425248393dc0aaebb0d20d1f383bc9a.m3u8?countryIso=US&isAuthorized=0&isWithVideoAds=1&isWithVideoAdsAlways=1"
    }
  },
  {
    "id": "95c75b53-789e-11ec-ae92-0242ac120002",
    "name": null,
    "ordinal": 7,
    "opening": {
      "stop": 177,
      "start": 127
    },
    "ending": {
      "stop": null,
      "start": null
    },
    "preview": {
      "src": null,
      "preview": null,
      "thumbnail": null,
      "optimized": {
        "src": null,
        "preview": null,
        "thumbnail": null
      }
    },
    "hls_480": "https://cache.libria.fun/videos/media/ts/8353/7/480/0c854b3638d813e32f6a599d6a95cd25.m3u8?countryIso=US&isAuthorized=0&isWithVideoAds=1&isWithVideoAdsAlways=1",
    "hls_720": "https://cache.libria.fun/videos/media/ts/8353/7/720/bcdfa9afcc3e1749f49849c35a3d1c93.m3u8?countryIso=US&isAuthorized=0&isWithVideoAds=1&isWithVideoAdsAlways=1",
    "hls_1080": null,
    "duration": 1455,
    "rutube_id": null,
    "youtube_id": null,
    "updated_at": "2019-04-03T22:28:19+00:00",
    "sort_order": 7,
    "release_id": 8353,
    "name_english": null,
    "_stream_links": {
      "hls_720": "https://cache.libria.fun/videos/media/ts/8353/7/720/bcdfa9afcc3e1749f49849c35a3d1c93.m3u8?countryIso=US&isAuthorized=0&isWithVideoAds=1&isWithVideoAdsAlways=1",
      "hls_480": "https://cache.libria.fun/videos/media/ts/8353/7/480/0c854b3638d813e32f6a599d6a95cd25.m3u8?countryIso=US&isAuthorized=0&isWithVideoAds=1&isWithVideoAdsAlways=1"
    }
  },
  {
    "id": "95c75bc4-789e-11ec-ae92-0242ac120002",
    "name": null,
    "ordinal": 8,
    "opening": {
      "stop": 96,
      "start": 46
    },
    "ending": {
      "stop": null,
      "start": null
    },
    "preview": {
      "src": null,
      "preview": null,
      "thumbnail": null,
      "optimized": {
        "src": null,
        "preview": null,
        "thumbnail": null
      }
    },
    "hls_480": "https://cache.libria.fun/videos/media/ts/8353/8/480/d220b2891454b77788331a796b6a9145.m3u8?countryIso=US&isAuthorized=0&isWithVideoAds=1&isWithVideoAdsAlways=1",
    "hls_720": "https://cache.libria.fun/videos/media/ts/8353/8/720/8617bcd5349e28afbc539d240aba2262.m3u8?countryIso=US&isAuthorized=0&isWithVideoAds=1&isWithVideoAdsAlways=1",
    "hls_1080": null,
    "duration": 1455,
    "rutube_id": null,
    "youtube_id": null,
    "updated_at": "2019-04-03T22:27:24+00:00",
    "sort_order": 8,
    "release_id": 8353,
    "name_english": null,
    "_stream_links": {
      "hls_720": "https://cache.libria.fun/videos/media/ts/8353/8/720/8617bcd5349e28afbc539d240aba2262.m3u8?countryIso=US&isAuthorized=0&isWithVideoAds=1&isWithVideoAdsAlways=1",
      "hls_480": "https://cache.libria.fun/videos/media/ts/8353/8/480/d220b2891454b77788331a796b6a9145.m3u8?countryIso=US&isAuthorized=0&isWithVideoAds=1&isWithVideoAdsAlways=1"
    }
  },
  {
    "id": "95c75c33-789e-11ec-ae92-0242ac120002",
    "name": null,
    "ordinal": 9,
    "opening": {
      "stop": 97,
      "start": 50
    },
    "ending": {
      "stop": null,
      "start": null
    },
    "preview": {
      "src": null,
      "preview": null,
      "thumbnail": null,
      "optimized": {
        "src": null,
        "preview": null,
        "thumbnail": null
      }
    },
    "hls_480": "https://cache.libria.fun/videos/media/ts/8353/9/480/557e1a393a3e6876e663b55a4a887085.m3u8?countryIso=US&isAuthorized=0&isWithVideoAds=1&isWithVideoAdsAlways=1",
    "hls_720": "https://cache.libria.fun/videos/media/ts/8353/9/720/50338e771fdca6602a9651b4a27476b7.m3u8?countryIso=US&isAuthorized=0&isWithVideoAds=1&isWithVideoAdsAlways=1",
    "hls_1080": null,
    "duration": 1455,
    "rutube_id": null,
    "youtube_id": null,
    "updated_at": "2019-04-03T22:27:24+00:00",
    "sort_order": 9,
    "release_id": 8353,
    "name_english": null,
    "_stream_links": {
      "hls_720": "https://cache.libria.fun/videos/media/ts/8353/9/720/50338e771fdca6602a9651b4a27476b7.m3u8?countryIso=US&isAuthorized=0&isWithVideoAds=1&isWithVideoAdsAlways=1",
      "hls_480": "https://cache.libria.fun/videos/media/ts/8353/9/480/557e1a393a3e6876e663b55a4a887085.m3u8?countryIso=US&isAuthorized=0&isWithVideoAds=1&isWithVideoAdsAlways=1"
    }
  },
  {
    "id": "95c75ca4-789e-11ec-ae92-0242ac120002",
    "name": null,
    "ordinal": 10,
    "opening": {
      "stop": 72,
      "start": 22
    },
    "ending": {
      "stop": null,
      "start": null
    },
    "preview": {
      "src": null,
      "preview": null,
      "thumbnail": null,
      "optimized": {
        "src": null,
        "preview": null,
        "thumbnail": null
      }
    },
    "hls_480": "https://cache.libria.fun/videos/media/ts/8353/10/480/a7df308c7a60db003d74e303549c72c9.m3u8?countryIso=US&isAuthorized=0&isWithVideoAds=1&isWithVideoAdsAlways=1",
    "hls_720": "https://cache.libria.fun/videos/media/ts/8353/10/720/73e74aab043627d915e6e60af3c89bf0.m3u8?countryIso=US&isAuthorized=0&isWithVideoAds=1&isWithVideoAdsAlways=1",
    "hls_1080": null,
    "duration": 1455,
    "rutube_id": null,
    "youtube_id": null,
    "updated_at": "2019-04-04T03:25:16+00:00",
    "sort_order": 10,
    "release_id": 8353,
    "name_english": null,
    "_stream_links": {
      "hls_720": "https://cache.libria.fun/videos/media/ts/8353/10/720/73e74aab043627d915e6e60af3c89bf0.m3u8?countryIso=US&isAuthorized=0&isWithVideoAds=1&isWithVideoAdsAlways=1",
      "hls_480": "https://cache.libria.fun/videos/media/ts/8353/10/480/a7df308c7a60db003d74e303549c72c9.m3u8?countryIso=US&isAuthorized=0&isWithVideoAds=1&isWithVideoAdsAlways=1"
    }
  },
  {
    "id": "95c75d17-789e-11ec-ae92-0242ac120002",
    "name": null,
    "ordinal": 11,
    "opening": {
      "stop": 116,
      "start": 66
    },
    "ending": {
      "stop": null,
      "start": null
    },
    "preview": {
      "src": null,
      "preview": null,
      "thumbnail": null,
      "optimized": {
        "src": null,
        "preview": null,
        "thumbnail": null
      }
    },
    "hls_480": "https://cache.libria.fun/videos/media/ts/8353/11/480/5324ea11f52fea7f1735a9bb0fba565c.m3u8?countryIso=US&isAuthorized=0&isWithVideoAds=1&isWithVideoAdsAlways=1",
    "hls_720": "https://cache.libria.fun/videos/media/ts/8353/11/720/a01c7bd6562819b0ce00d39d75cf03c9.m3u8?countryIso=US&isAuthorized=0&isWithVideoAds=1&isWithVideoAdsAlways=1",
    "hls_1080": null,
    "duration": 1454,
    "rutube_id": null,
    "youtube_id": null,
    "updated_at": "2019-04-04T03:24:23+00:00",
    "sort_order": 11,
    "release_id": 8353,
    "name_english": null,
    "_stream_links": {
      "hls_720": "https://cache.libria.fun/videos/media/ts/8353/11/720/a01c7bd6562819b0ce00d39d75cf03c9.m3u8?countryIso=US&isAuthorized=0&isWithVideoAds=1&isWithVideoAdsAlways=1",
      "hls_480": "https://cache.libria.fun/videos/media/ts/8353/11/480/5324ea11f52fea7f1735a9bb0fba565c.m3u8?countryIso=US&isAuthorized=0&isWithVideoAds=1&isWithVideoAdsAlways=1"
    }
  },
  {
    "id": "95c75d87-789e-11ec-ae92-0242ac120002",
    "name": null,
    "ordinal": 12,
    "opening": {
      "stop": null,
      "start": null
    },
    "ending": {
      "stop": null,
      "start": null
    },
    "preview": {
      "src": null,
      "preview": null,
      "thumbnail": null,
      "optimized": {
        "src": null,
        "preview": null,
        "thumbnail": null
      }
    },
    "hls_480": "https://cache.libria.fun/videos/media/ts/8353/12/480/6d00ddab0f8102f958a4ee5fb8338045.m3u8?countryIso=US&isAuthorized=0&isWithVideoAds=1&isWithVideoAdsAlways=1",
    "hls_720": "https://cache.libria.fun/videos/media/ts/8353/12/720/7b87c04f25397b221d6d17ec6cadff43.m3u8?countryIso=US&isAuthorized=0&isWithVideoAds=1&isWithVideoAdsAlways=1",
    "hls_1080": null,
    "duration": 1455,
    "rutube_id": null,
    "youtube_id": null,
    "updated_at": "2019-04-04T03:24:23+00:00",
    "sort_order": 12,
    "release_id": 8353,
    "name_english": null,
    "_stream_links": {
      "hls_720": "https://cache.libria.fun/videos/media/ts/8353/12/720/7b87c04f25397b221d6d17ec6cadff43.m3u8?countryIso=US&isAuthorized=0&isWithVideoAds=1&isWithVideoAdsAlways=1",
      "hls_480": "https://cache.libria.fun/videos/media/ts/8353/12/480/6d00ddab0f8102f958a4ee5fb8338045.m3u8?countryIso=US&isAuthorized=0&isWithVideoAds=1&isWithVideoAdsAlways=1"
    }
  },
  {
    "id": "95c75df8-789e-11ec-ae92-0242ac120002",
    "name": null,
    "ordinal": 13,
    "opening": {
      "stop": null,
      "start": null
    },
    "ending": {
      "stop": null,
      "start": null
    },
    "preview": {
      "src": null,
      "preview": null,
      "thumbnail": null,
      "optimized": {
        "src": null,
        "preview": null,
        "thumbnail": null
      }
    },
    "hls_480": "https://cache.libria.fun/videos/media/ts/8353/13/480/43b33edc7b9c6461aba1902aca3135aa.m3u8?countryIso=US&isAuthorized=0&isWithVideoAds=1&isWithVideoAdsAlways=1",
    "hls_720": "https://cache.libria.fun/videos/media/ts/8353/13/720/f83e23a6a0e38a41fc3fb019d404d72b.m3u8?countryIso=US&isAuthorized=0&isWithVideoAds=1&isWithVideoAdsAlways=1",
    "hls_1080": null,
    "duration": 1455,
    "rutube_id": null,
    "youtube_id": null,
    "updated_at": "2019-04-04T03:23:39+00:00",
    "sort_order": 13,
    "release_id": 8353,
    "name_english": null,
    "_stream_links": {
      "hls_720": "https://cache.libria.fun/videos/media/ts/8353/13/720/f83e23a6a0e38a41fc3fb019d404d72b.m3u8?countryIso=US&isAuthorized=0&isWithVideoAds=1&isWithVideoAdsAlways=1",
      "hls_480": "https://cache.libria.fun/videos/media/ts/8353/13/480/43b33edc7b9c6461aba1902aca3135aa.m3u8?countryIso=US&isAuthorized=0&isWithVideoAds=1&isWithVideoAdsAlways=1"
    }
  }
]