[
  {
    "id": "95daee4c-789e-11ec-ae92-0242ac120002",
    "name": null,
    "ordinal": 1,
    "opening": {
      "stop": 309,
      "start": 295
    },
    "ending": {
      "stop": null,
      "start": null
    },
    "preview": {
      "src": null,
      "preview": null,
      "thumbnail": null,
      "optimized": {
        "src": null,
        "preview": null,
        "thumbnail": null
      }
    },
    "hls_480": "https://cache.libria.fun/videos/media/ts/8991/1/480/486601b50fb2c976f8a8ab47b5926146.m3u8?countryIso=US&isAuthorized=0&isWithVideoAds=1&isWithVideoAdsAlways=1",
    "hls_720": "https://cache.libria.fun/videos/media/ts/8991/1/720/bc9112ad3e7ffc666cf4419e9c41501f.m3u8?countryIso=US&isAuthorized=0&isWithVideoAds=1&isWithVideoAdsAlways=1",
    "hls_1080": "https://cache.libria.fun/videos/media/ts/8991/1/1080/ba552fc1f36044f46059575c3480ccda.m3u8?countryIso=US&isAuthorized=0&isWithVideoAds=1&isWithVideoAdsAlways=1",
    "duration": 1473,
    "rutube_id": null,
    "youtube_id": null,
    "updated_at": "2021-05-25T22:34:18+00:00",
    "sort_order": 1,
    "release_id": 8991,
    "name_english": null,
    "_stream_links": {
      "hls_1080": "https://cache.libria.fun/videos/media/ts/8991/1/1080/ba552fc1f36044f46059575c3480ccda.m3u8?countryIso=US&isAuthorized=0&isWithVideoAds=1&isWithVideoAdsAlways=1",
      "hls_720": "https://cache.libria.fun/videos/media/ts/8991/1/720/bc9112ad3e7ffc666cf4419e9c41501f.m3u8?countryIso=US&isAuthorized=0&isWithVideoAds=1&isWithVideoAdsAlways=1",
      "hls_480": "https://cache.libria.fun/videos/media/ts/8991/1/480/486601b50fb2c976f8a8ab47b5926146.m3u8?countryIso=US&isAuthorized=0&isWithVideoAds=1&isWithVideoAdsAlways=1"
    }
  },
  {
    "id": "95daeec5-789e-11ec-ae92-0242ac120002",
    "name": null,
    "ordinal": 2,
    "opening": {
      "stop": 75,
      "start": 60
    },
    "ending": {
      "stop": null,
      "start": null
    },
    "preview": {
      "src": null,
      "preview": null,
      "thumbnail": null,
      "optimized": {
        "src": null,
        "preview": null,
        "thumbnail": null
      }
    },
    "hls_480": "https://cache.libria.fun/videos/media/ts/8991/2/480/fa46e22c493f7efa3234647aeb4f92aa.m3u8?countryIso=US&isAuthorized=0&isWithVideoAds=1&isWithVideoAdsAlways=1",
    "hls_720": "https://cache.libria.fun/videos/media/ts/8991/2/720/f531cf0a4f6272a22a1f00f6607e0e43.m3u8?countryIso=US&isAuthorized=0&isWithVideoAds=1&isWithVideoAdsAlways=1",
    "hls_1080": "https://cache.libria.fun/videos/media/ts/8991/2/1080/74dce7894337d9e8dd4a4d3cf3f8ed8b.m3u8?countryIso=US&isAuthorized=0&isWithVideoAds=1&isWithVideoAdsAlways=1",
    "duration": 1409,
    "rutube_id": null,
    "youtube_id": null,
    "updated_at": "2021-05-25T23:54:03+00:00",
    "sort_order": 2,
    "release_id": 8991,
    "name_english": null,
    "_stream_links": {
      "hls_1080": "https://cache.libria.fun/videos/media/ts/8991/2/1080/74dce7894337d9e8dd4a4d3cf3f8ed8b.m3u8?countryIso=US&isAuthorized=0&isWithVideoAds=1&isWithVideoAdsAlways=1",
      "hls_720": "https://cache.libria.fun/videos/media/ts/8991/2/720/f531cf0a4f6272a22a1f00f6607e0e43.m3u8?countryIso=US&isAuthorized=0&isWithVideoAds=1&isWithVideoAdsAlways=1",
      "hls_480": "https://cache.libria.fun/videos/media/ts/8991/2/480/fa46e22c493f7efa3234647aeb4f92aa.m3u8?countryIso=US&isAuthorized=0&isWithVideoAds=1&isWithVideoAdsAlways=1"
    }
  },
  {
    "id": "95daef42-789e-11ec-ae92-0242ac120002",
    "name": null,
    "ordinal": 3,
    "opening": {
      "stop": null,
      "start": null
    },
    "ending": {
      "stop": null,
      "start": null
    },
    "preview": {
      "src": null,
      "preview": null,
      "thumbnail": null,
      "optimized": {
        "src": null,
        "preview": null,
        "thumbnail": null
      }
    },
    "hls_480": "https://cache.libria.fun/videos/media/ts/8991/3/480/0a9c0aa388569cadb784a333592db4ea.m3u8?countryIso=US&isAuthorized=0&isWithVideoAds=1&isWithVideoAdsAlways=1",
    "hls_720": "https://cache.libria.fun/videos/media/ts/8991/3/720/83c02ed3cd3bbd15dd5d451f5f8bf3c3.m3u8?countryIso=US&isAuthorized=0&isWithVideoAds=1&isWithVideoAdsAlways=1",
    "hls_1080": "https://cache.libria.fun/videos/media/ts/8991/3/1080/8446fc7f955c1b68581a7356368a9e09.m3u8?countryIso=US&isAuthorized=0&isWithVideoAds=1&isWithVideoAdsAlways=1",
    "duration": 1440,
    "rutube_id": null,
    "youtube_id": null,
    "updated_at": "2021-05-25T23:53:10+00:00",
    "sort_order": 3,
    "release_id": 8991,
    "name_english": null,
    "_stream_links": {
      "hls_1080": "https://cache.libria.fun/videos/media/ts/8991/3/1080/8446fc7f955c1b68581a7356368a9e09.m3u8?countryIso=US&isAuthorized=0&isWithVideoAds=1&isWithVideoAdsAlways=1",
      "hls_720": "https://cache.libria.fun/videos/media/ts/8991/3/720/83c02ed3cd3bbd15dd5d451f5f8bf3c3.m3u8?countryIso=US&isAuthorized=0&isWithVideoAds=1&isWithVideoAdsAlways=1",
      "hls_480": "https://cache.libria.fun/videos/media/ts/8991/3/480/0a9c0aa388569cadb784a333592db4ea.m3u8?countryIso=US&isAuthorized=0&isWithVideoAds=1&isWithVideoAdsAlways=1"
    }
  },
  {
    "id": "95daefba-789e-11ec-ae92-0242ac120002",
    "name": null,
    "ordinal": 4,
    "opening": {
      "stop": 75,
      "start": 61
    },
    "ending": {
      "stop": null,
      "start": null
    },
    "preview": {
      "src": null,
      "preview": null,
      "thumbnail": null,
      "optimized": {
        "src": null,
        "preview": null,
        "thumbnail": null
      }
    },
    "hls_480": "https://cache.libria.fun/videos/media/ts/8991/4/480/97b2511bbd49a01e03ed4f07be5cfbb8.m3u8?countryIso=US&isAuthorized=0&isWithVideoAds=1&isWithVideoAdsAlways=1",
    "hls_720": "https://cache.libria.fun/videos/media/ts/8991/4/720/ab8aefb0752e2b10f88b7913a31075a1.m3u8?countryIso=US&isAuthorized=0&isWithVideoAds=1&isWithVideoAdsAlways=1",
    "hls_1080": "https://cache.libria.fun/videos/media/ts/8991/4/1080/5a8904e06ce623a713f346932d5cf2a2.m3u8?countryIso=US&isAuthorized=0&isWithVideoAds=1&isWithVideoAdsAlways=1",
    "duration": 1436,
    "rutube_id": null,
    "youtube_id": null,
    "updated_at": "2021-05-25T23:53:09+00:00",
    "sort_order": 4,
    "release_id": 8991,
    "name_english": null,
    "_stream_links": {
      "hls_1080": "https://cache.libria.fun/videos/media/ts/8991/4/1080/5a8904e06ce623a713f346932d5cf2a2.m3u8?countryIso=US&isAuthorized=0&isWithVideoAds=1&isWithVideoAdsAlways=1",
      "hls_720": "https://cache.libria.fun/videos/media/ts/8991/4/720/ab8aefb0752e2b10f88b7913a31075a1.m3u8?countryIso=US&isAuthorized=0&isWithVideoAds=1&isWithVideoAdsAlways=1",
      "hls_480": "https://cache.libria.fun/videos/media/ts/8991/4/480/97b2511bbd49a01e03ed4f07be5cfbb8.m3u8?countryIso=US&isAuthorized=0&isWithVideoAds=1&isWithVideoAdsAlways=1"
    }
  },
  {
    "id": "95daf034-789e-11ec-ae92-0242ac120002",
    "name": null,
    "ordinal": 5,
    "opening": {
      "stop": null,
      "start": null
    },
    "ending": {
      "stop": null,
      "start": null
    },
    "preview": {
      "src": null,
      "preview": null,
      "thumbnail": null,
      "optimized": {
        "src": null,
        "preview": null,
        "thumbnail": null
      }
    },
    "hls_480": "https://cache.libria.fun/videos/media/ts/8991/5/480/4228241bf333cc85b4acbaf2b2d09815.m3u8?countryIso=US&isAuthorized=0&isWithVideoAds=1&isWithVideoAdsAlways=1",
    "hls_720": "https://cache.libria.fun/videos/media/ts/8991/5/720/2130b052e279256a14798cfb790b351e.m3u8?countryIso=US&isAuthorized=0&isWithVideoAds=1&isWithVideoAdsAlways=1",
    "hls_1080": "https://cache.libria.fun/videos/media/ts/8991/5/1080/d0e2ba35d033aba4ca88608784bd96b6.m3u8?countryIso=US&isAuthorized=0&isWithVideoAds=1&isWithVideoAdsAlways=1",
    "duration": 1391,
    "rutube_id": null,
    "youtube_id": null,
    "updated_at": "2021-05-25T23:52:14+00:00",
    "sort_order": 5,
    "release_id": 8991,
    "name_english": null,
    "_stream_links": {
      "hls_1080": "https://cache.libria.fun/videos/media/ts/8991/5/1080/d0e2ba35d033aba4ca88608784bd96b6.m3u8?countryIso=US&isAuthorized=0&isWithVideoAds=1&isWithVideoAdsAlways=1",
      "hls_720": "https://cache.libria.fun/videos/media/ts/8991/5/720/2130b052e279256a14798cfb790b351e.m3u8?countryIso=US&isAuthorized=0&isWithVideoAds=1&isWithVideoAdsAlways=1",
      "hls_480": "https://cache.libria.fun/videos/media/ts/8991/5/480/4228241bf333cc85b4acbaf2b2d09815.m3u8?countryIso=US&isAuthorized=0&isWithVideoAds=1&isWithVideoAdsAlways=1"
    }
  },
  {
    "id": "95daf0ae-789e-11ec-ae92-0242ac120002",
    "name": null,
    "ordinal": 6,
    "opening": {
      "stop": null,
      "start": null
    },
    "ending": {
      "stop": null,
      "start": null
    },
    "preview": {
      "src": null,
      "preview": null,
      "thumbnail": null,
      "optimized": {
        "src": null,
        "preview": null,
        "thumbnail": null
      }
    },
    "hls_480": "https://cache.libria.fun/videos/media/ts/8991/6/480/6903d8066fa721a7883b1863856bcbf1.m3u8?countryIso=US&isAuthorized=0&isWithVideoAds=1&isWithVideoAdsAlways=1",
    "hls_720": "https://cache.libria.fun/videos/media/ts/8991/6/720/61203f64e853565825695f093439432b.m3u8?countryIso=US&isAuthorized=0&isWithVideoAds=1&isWithVideoAdsAlways=1",
    "hls_1080": "https://cache.libria.fun/videos/media/ts/8991/6/1080/5032e1f0c24d0e5ad5bf1f4604430b99.m3u8?countryIso=US&isAuthorized=0&isWithVideoAds=1&isWithVideoAdsAlways=1",
    "duration": 1380,
    "rutube_id": null,
    "youtube_id": null,
    "updated_at": "2021-05-26T16:20:53+00:00",
    "sort_order": 6,
    "release_id": 8991,
    "name_english": null,
    "_stream_links": {
      "hls_1080": "https://cache.libria.fun/videos/media/ts/8991/6/1080/5032e1f0c24d0e5ad5bf1f4604430b99.m3u8?countryIso=US&isAuthorized=0&isWithVideoAds=1&isWithVideoAdsAlways=1",
      "hls_720": "https://cache.libria.fun/videos/media/ts/8991/6/720/61203f64e853565825695f093439432b.m3u8?countryIso=US&isAuthorized=0&isWithVideoAds=1&isWithVideoAdsAlways=1",
      "hls_480": "https://cache.libria.fun/videos/media/ts/8991/6/480/6903d8066fa721a7883b1863856bcbf1.m3u8?countryIso=US&isAuthorized=0&isWithVideoAds=1&isWithVideoAdsAlways=1"
    }
  }
]